octavus_ai/__init__.py
octavus_ai-0.0.1.dist-info/METADATA
octavus_ai-0.0.1.dist-info/WHEEL
octavus_ai-0.0.1.dist-info/licenses/LICENSE
octavus_ai-0.0.1.dist-info/RECORD
